litevectordb/__init__.py
litevectordb/client.py
litevectordb/embeddings.py
litevectordb/memory.py
litevectordb/py.typed
litevectordb/vector_store.py
litevectordb/index/__init__.py
litevectordb/index/base.py
litevectordb/index/linear.py
litevectordb-0.2.0.dist-info/licenses/LICENSE
litevectordb-0.2.0.dist-info/METADATA
litevectordb-0.2.0.dist-info/WHEEL
litevectordb-0.2.0.dist-info/top_level.txt
litevectordb-0.2.0.dist-info/RECORD
