Metadata-Version: 2.4
Name: litevectordb
Version: 0.2.0
Summary: Banco de dados vetorial local, leve e simples. Sem servidor, sem complicação.
Author-email: Ederson Melo <edersonmelo@outlook.com>
Project-URL: Homepage, https://github.com/litevectordb/litevectordb
Project-URL: Documentation, https://github.com/litevectordb/litevectordb#readme
Project-URL: Repository, https://github.com/litevectordb/litevectordb
Project-URL: Issues, https://github.com/litevectordb/litevectordb/issues
Keywords: vector,database,embeddings,semantic-search,sqlite,chroma
Classifier: Development Status :: 4 - Beta
Classifier: Intended Audience :: Developers
Classifier: License :: OSI Approved :: MIT License
Classifier: Programming Language :: Python :: 3
Classifier: Programming Language :: Python :: 3.9
Classifier: Programming Language :: Python :: 3.10
Classifier: Programming Language :: Python :: 3.11
Classifier: Programming Language :: Python :: 3.12
Classifier: Topic :: Database
Classifier: Topic :: Scientific/Engineering :: Artificial Intelligence
Requires-Python: >=3.9
License-File: LICENSE
Requires-Dist: numpy>=1.21.0
Provides-Extra: api
Requires-Dist: fastapi>=0.100.0; extra == "api"
Requires-Dist: uvicorn[standard]>=0.23.0; extra == "api"
Requires-Dist: pydantic>=2.0.0; extra == "api"
Dynamic: license-file
